google_api_wrapper-2.0.0a1.dist-info/DESCRIPTION.rst
google_api_wrapper-2.0.0a1.dist-info/METADATA
google_api_wrapper-2.0.0a1.dist-info/RECORD
google_api_wrapper-2.0.0a1.dist-info/WHEEL
google_api_wrapper-2.0.0a1.dist-info/metadata.json
google_api_wrapper-2.0.0a1.dist-info/top_level.txt
googleapiwrapper/Cloud.py
googleapiwrapper/Compute.py
googleapiwrapper/DeploymentManager.py
googleapiwrapper/Exceptions.py
googleapiwrapper/Iam.py
googleapiwrapper/__init__.py
