Metadata-Version: 2.0
Name: google-api-wrapper
Version: 2.0.0a1
Summary: Simple wrapper for Google APIs
Home-page: https://bitbucket.org/infolinks/google-api-wrapper
Author: Arik Kfir
Author-email: arik@infolinks.com
License: MIT
Keywords: google,cloud,api,wrapper,compute,iam,deployment
Platform: UNKNOWN
Classifier: Development Status :: 3 - Alpha
Classifier: Intended Audience :: Developers
Classifier: License :: OSI Approved :: MIT License
Classifier: Programming Language :: Python :: 3 :: Only
Classifier: Programming Language :: Python :: 3.5
Classifier: Topic :: Software Development
Classifier: Topic :: Software Development :: Libraries
Classifier: Topic :: Software Development :: Libraries :: Python Modules
Classifier: Topic :: System :: Software Distribution
Classifier: Topic :: System :: Systems Administration
Requires-Dist: google-api-python-client
